ternviz/__init__.py
ternviz/bot.py
ternviz/lib.py
ternviz/main.py
ternviz/version.py
ternviz/vmd/render-lq.vmd
ternviz/vmd/render-pdb.vmd
ternviz/vmd/render-points.vmd
ternviz/vmd/render.vmd
ternviz-0.6.3.dist-info/LICENSE
ternviz-0.6.3.dist-info/METADATA
ternviz-0.6.3.dist-info/WHEEL
ternviz-0.6.3.dist-info/entry_points.txt
ternviz-0.6.3.dist-info/top_level.txt
ternviz-0.6.3.dist-info/zip-safe
ternviz-0.6.3.dist-info/RECORD
