Metadata-Version: 2.1
Name: ternviz
Version: 0.6.3
Summary: Render SMILES into 3D video
Home-page: https://github.com/whitead/ternviz
Author: Andrew White
Author-email: andrew.white@rochester.edu
License: MIT
Classifier: Programming Language :: Python :: 3
Classifier: License :: OSI Approved :: MIT License
Classifier: Operating System :: OS Independent
Classifier: Topic :: Scientific/Engineering :: Chemistry
License-File: LICENSE
Requires-Dist: click
Requires-Dist: rdkit-pypi
Requires-Dist: requests
Requires-Dist: importlib-resources
Requires-Dist: MDAnalysis
Provides-Extra: bot
Requires-Dist: tweepy ; extra == 'bot'
Requires-Dist: python-dotenv ; extra == 'bot'
